{
  "prev_csv": "hero_main_banners_2026-04-20.csv",
  "curr_csv": "hero_main_banners_2026-04-21.csv",
  "summary": {
    "added": 2,
    "removed": 1,
    "changed": 8,
    "brands_touched": 4,
    "subtypes": {
      "title_changed": 1,
      "image_changed": 6,
      "rank_shift": 1
    }
  },
  "by_brand": {
    "arcteryx": {
      "added": 0,
      "removed": 0,
      "changed": 1,
      "subtypes": {
        "title_changed": 1
      }
    },
    "blackyak": {
      "added": 1,
      "removed": 0,
      "changed": 1,
      "subtypes": {
        "rank_shift": 1,
        "image_changed": 1,
        "landing_text_changed": 1,
        "extractor_changed": 1
      }
    },
    "k2": {
      "added": 1,
      "removed": 0,
      "changed": 2,
      "subtypes": {
        "image_changed": 2,
        "title_changed": 1
      }
    },
    "montbell": {
      "added": 0,
      "removed": 1,
      "changed": 4,
      "subtypes": {
        "rank_shift": 4,
        "image_changed": 3
      }
    }
  },
  "added": [
    {
      "date": "2026-04-21",
      "brand_key": "blackyak",
      "brand_name": "Black Yak",
      "rank": "1",
      "title": "MEMBERSHIP LUCK 30만원이상 구매 시 기다리는 혜택",
      "href": "https://www.byn.kr/_exh/?no=2123&utm_source=BY_pc&utm_medium=pc_by_banner_mb",
      "href_clean": "https://www.byn.kr/_exh/?no=2123",
      "plan_start": "",
      "plan_end": "",
      "img_url": "https://cdn.byn.kr/real/_data/banner/c4b7ec244f40ea63ab01bd617e827db1.jpg",
      "img_local": "blackyak_1_cf3ce6b821.jpg",
      "img_status": "ok",
      "img_w": "1100",
      "img_h": "538",
      "img_bytes": "20495",
      "img_signature": "e130e52f0f1aa84a",
      "brand_resolved_url": "https://www.byn.kr/blackyak",
      "extract_source": "blackyak_swiper",
      "confidence_score": "0.93",
      "is_fallback": "0",
      "is_primary_hero": "1",
      "landing_title": "목표 달성 후 응모만 해도 100% 당첨!",
      "landing_subtitle": "4월 1일부터 30일까지 30만원 이상 구매하고 럭키박스 참여하세요.",
      "landing_summary": "BYN 블랙야크 공식몰입니다.",
      "landing_keywords": "신발",
      "landing_category": "풋웨어",
      "landing_text_status": "ok"
    },
    {
      "date": "2026-04-21",
      "brand_key": "k2",
      "brand_name": "K2",
      "rank": "4",
      "title": "메인 배너",
      "href": "",
      "href_clean": "",
      "plan_start": "",
      "plan_end": "",
      "img_url": "https://contents.k-village.co.kr/VSL_con/20260313/img/1773384075790.png",
      "img_local": "k2_19_7d4524691a.jpg",
      "img_status": "ok",
      "img_w": "420",
      "img_h": "412",
      "img_bytes": "21892",
      "img_signature": "88d5362a3b2bfac9",
      "brand_resolved_url": "https://www.k-village.co.kr/K2",
      "extract_source": "generic_fallback",
      "confidence_score": "0.55",
      "is_fallback": "1",
      "is_primary_hero": "0",
      "landing_title": "",
      "landing_subtitle": "",
      "landing_summary": "",
      "landing_keywords": "",
      "landing_category": "",
      "landing_text_status": "skipped"
    }
  ],
  "removed": [
    {
      "date": "2026-04-20",
      "brand_key": "montbell",
      "brand_name": "Montbell",
      "rank": "2",
      "title": "몽벨 용산직영점 리뉴얼 오픈 안내",
      "href": "https://www.instagram.com/montbell_kr/",
      "href_clean": "https://www.instagram.com/montbell_kr/",
      "plan_start": "",
      "plan_end": "",
      "img_url": "https://www.montbell.co.kr/data/editor/2604/5a653dc55619307551e3af0e0db564f3_1776057920_0211.jpg",
      "img_local": "montbell_1_9b65908792.jpg",
      "img_status": "ok",
      "img_w": "450",
      "img_h": "563",
      "img_bytes": "47553",
      "img_signature": "62898485be35824e",
      "brand_resolved_url": "https://www.montbell.co.kr/",
      "extract_source": "generic_fallback",
      "confidence_score": "0.55",
      "is_fallback": "1",
      "is_primary_hero": "0",
      "landing_title": "",
      "landing_subtitle": "",
      "landing_summary": "",
      "landing_keywords": "",
      "landing_category": "",
      "landing_text_status": "skipped"
    }
  ],
  "changed": [
    {
      "identity": "href:https://arcteryx.co.kr/products/category/145",
      "brand_key": "arcteryx",
      "rank": "3",
      "prev_rank": "3",
      "subtype": "title_changed",
      "subtypes": [
        "title_changed"
      ],
      "diffs": {
        "title": {
          "prev": "VEILANCE",
          "curr": "Heliad 15 Backpack"
        }
      },
      "prev": {
        "date": "2026-04-20",
        "brand_key": "arcteryx",
        "brand_name": "Arc'teryx",
        "rank": "3",
        "title": "VEILANCE",
        "href": "https://arcteryx.co.kr/products/category/145",
        "href_clean": "https://arcteryx.co.kr/products/category/145",
        "plan_start": "",
        "plan_end": "",
        "img_url": "https://public.arcteryx.co.kr/images/banner/91zbspe3GADpq7d2iwFCDErIPrvBg2L3TjwB9pbg.jpg",
        "img_local": "arcteryx_4_6d16e6e00f.jpg",
        "img_status": "ok",
        "img_w": "1080",
        "img_h": "1080",
        "img_bytes": "105863",
        "img_signature": "69a7468d9eef1151",
        "brand_resolved_url": "https://arcteryx.co.kr/",
        "extract_source": "generic_fallback",
        "confidence_score": "0.55",
        "is_fallback": "1",
        "is_primary_hero": "0",
        "landing_title": "",
        "landing_subtitle": "",
        "landing_summary": "",
        "landing_keywords": "",
        "landing_category": "",
        "landing_text_status": "skipped"
      },
      "curr": {
        "date": "2026-04-21",
        "brand_key": "arcteryx",
        "brand_name": "Arc'teryx",
        "rank": "3",
        "title": "Heliad 15 Backpack",
        "href": "https://arcteryx.co.kr/products/category/145",
        "href_clean": "https://arcteryx.co.kr/products/category/145",
        "plan_start": "",
        "plan_end": "",
        "img_url": "https://public.arcteryx.co.kr/images/banner/91zbspe3GADpq7d2iwFCDErIPrvBg2L3TjwB9pbg.jpg",
        "img_local": "arcteryx_4_6d16e6e00f.jpg",
        "img_status": "ok",
        "img_w": "1080",
        "img_h": "1080",
        "img_bytes": "105863",
        "img_signature": "69a7468d9eef1151",
        "brand_resolved_url": "https://arcteryx.co.kr/",
        "extract_source": "generic_fallback",
        "confidence_score": "0.55",
        "is_fallback": "1",
        "is_primary_hero": "0",
        "landing_title": "",
        "landing_subtitle": "",
        "landing_summary": "",
        "landing_keywords": "",
        "landing_category": "",
        "landing_text_status": "skipped"
      }
    },
    {
      "identity": "href:https://www.byn.kr/_exh/?no=2112",
      "brand_key": "blackyak",
      "rank": "5",
      "prev_rank": "1",
      "subtype": "image_changed",
      "subtypes": [
        "rank_shift",
        "image_changed",
        "landing_text_changed",
        "extractor_changed"
      ],
      "diffs": {
        "rank": {
          "prev": "1",
          "curr": "5"
        },
        "img_local": {
          "prev": "blackyak_1_5ba184aa23.jpg",
          "curr": "blackyak_5_5ba184aa23.jpg"
        },
        "is_primary_hero": {
          "prev": "1",
          "curr": "0"
        },
        "landing_title": {
          "prev": "원활한 이벤트참여 진행을 위해로그인 하시겠습니까?",
          "curr": ""
        },
        "landing_summary": {
          "prev": "BYN 블랙야크 공식몰입니다.",
          "curr": ""
        },
        "landing_keywords": {
          "prev": "신발",
          "curr": ""
        },
        "landing_category": {
          "prev": "풋웨어",
          "curr": ""
        },
        "landing_text_status": {
          "prev": "ok",
          "curr": "skipped"
        }
      },
      "prev": {
        "date": "2026-04-20",
        "brand_key": "blackyak",
        "brand_name": "Black Yak",
        "rank": "1",
        "title": "TRAIL RUNNING 이규호 X 블랙야크",
        "href": "https://www.byn.kr/_exh/?no=2112&utm_source=BY_pc&utm_medium=pc_by_main_banner_tr",
        "href_clean": "https://www.byn.kr/_exh/?no=2112",
        "plan_start": "",
        "plan_end": "",
        "img_url": "https://cdn.byn.kr/real/_data/banner/c9a46590921bcb48a3c9eaf6cf627c72.jpg",
        "img_local": "blackyak_1_5ba184aa23.jpg",
        "img_status": "ok",
        "img_w": "1100",
        "img_h": "538",
        "img_bytes": "147571",
        "img_signature": "ef53032cd5b9eabe",
        "brand_resolved_url": "https://www.byn.kr/blackyak",
        "extract_source": "blackyak_swiper",
        "confidence_score": "0.93",
        "is_fallback": "0",
        "is_primary_hero": "1",
        "landing_title": "원활한 이벤트참여 진행을 위해로그인 하시겠습니까?",
        "landing_subtitle": "",
        "landing_summary": "BYN 블랙야크 공식몰입니다.",
        "landing_keywords": "신발",
        "landing_category": "풋웨어",
        "landing_text_status": "ok"
      },
      "curr": {
        "date": "2026-04-21",
        "brand_key": "blackyak",
        "brand_name": "Black Yak",
        "rank": "5",
        "title": "TRAIL RUNNING 이규호 X 블랙야크",
        "href": "https://www.byn.kr/_exh/?no=2112&utm_source=BY_pc&utm_medium=pc_by_main_banner_tr",
        "href_clean": "https://www.byn.kr/_exh/?no=2112",
        "plan_start": "",
        "plan_end": "",
        "img_url": "https://cdn.byn.kr/real/_data/banner/c9a46590921bcb48a3c9eaf6cf627c72.jpg",
        "img_local": "blackyak_5_5ba184aa23.jpg",
        "img_status": "ok",
        "img_w": "1100",
        "img_h": "538",
        "img_bytes": "147571",
        "img_signature": "ef53032cd5b9eabe",
        "brand_resolved_url": "https://www.byn.kr/blackyak",
        "extract_source": "blackyak_swiper",
        "confidence_score": "0.93",
        "is_fallback": "0",
        "is_primary_hero": "0",
        "landing_title": "",
        "landing_subtitle": "",
        "landing_summary": "",
        "landing_keywords": "",
        "landing_category": "",
        "landing_text_status": "skipped"
      }
    },
    {
      "identity": "href:javascript:void(0)",
      "brand_key": "k2",
      "rank": "1",
      "prev_rank": "1",
      "subtype": "image_changed",
      "subtypes": [
        "image_changed",
        "title_changed"
      ],
      "diffs": {
        "title": {
          "prev": "하늘이 내린 신발, 플라이하이크 스카이 신기만 해도 세상 모든 길이 편해지니까",
          "curr": "어디서든 잘 나간다, 탁월한 쿠셔닝의 멀티로드화 MULTIFLY 라이저"
        },
        "img_url": {
          "prev": "https://contents.k-village.co.kr/VSL_con/20260227/img/1772173626245.jpg/k2dims/optimize",
          "curr": "https://contents.k-village.co.kr/VSL_con/20260312/img/1773302339495.jpg/k2dims/optimize"
        },
        "img_local": {
          "prev": "k2_1_28873e4597.jpg",
          "curr": "k2_1_b80a05f771.jpg"
        },
        "img_signature": {
          "prev": "17f7b1d2a0925993",
          "curr": "155b3e8a2814dd01"
        }
      },
      "prev": {
        "date": "2026-04-20",
        "brand_key": "k2",
        "brand_name": "K2",
        "rank": "1",
        "title": "하늘이 내린 신발, 플라이하이크 스카이 신기만 해도 세상 모든 길이 편해지니까",
        "href": "javascript:void(0)",
        "href_clean": "javascript:void(0)",
        "plan_start": "",
        "plan_end": "",
        "img_url": "https://contents.k-village.co.kr/VSL_con/20260227/img/1772173626245.jpg/k2dims/optimize",
        "img_local": "k2_1_28873e4597.jpg",
        "img_status": "ok",
        "img_w": "1100",
        "img_h": "401",
        "img_bytes": "108806",
        "img_signature": "17f7b1d2a0925993",
        "brand_resolved_url": "https://www.k-village.co.kr/K2",
        "extract_source": "hero_slider_container",
        "confidence_score": "0.88",
        "is_fallback": "0",
        "is_primary_hero": "1",
        "landing_title": "",
        "landing_subtitle": "",
        "landing_summary": "",
        "landing_keywords": "",
        "landing_category": "",
        "landing_text_status": "exception"
      },
      "curr": {
        "date": "2026-04-21",
        "brand_key": "k2",
        "brand_name": "K2",
        "rank": "1",
        "title": "어디서든 잘 나간다, 탁월한 쿠셔닝의 멀티로드화 MULTIFLY 라이저",
        "href": "javascript:void(0)",
        "href_clean": "javascript:void(0)",
        "plan_start": "",
        "plan_end": "",
        "img_url": "https://contents.k-village.co.kr/VSL_con/20260312/img/1773302339495.jpg/k2dims/optimize",
        "img_local": "k2_1_b80a05f771.jpg",
        "img_status": "ok",
        "img_w": "1100",
        "img_h": "401",
        "img_bytes": "48418",
        "img_signature": "155b3e8a2814dd01",
        "brand_resolved_url": "https://www.k-village.co.kr/K2",
        "extract_source": "hero_slider_container",
        "confidence_score": "0.88",
        "is_fallback": "0",
        "is_primary_hero": "1",
        "landing_title": "",
        "landing_subtitle": "",
        "landing_summary": "",
        "landing_keywords": "",
        "landing_category": "",
        "landing_text_status": "exception"
      }
    },
    {
      "identity": "href:https://www.k-village.co.kr/goods/KWP26146O8",
      "brand_key": "k2",
      "rank": "3",
      "prev_rank": "3",
      "subtype": "image_changed",
      "subtypes": [
        "image_changed"
      ],
      "diffs": {
        "img_local": {
          "prev": "k2_11_400a5f51c3.jpg",
          "curr": "k2_12_400a5f51c3.jpg"
        }
      },
      "prev": {
        "date": "2026-04-20",
        "brand_key": "k2",
        "brand_name": "K2",
        "rank": "3",
        "title": "K2",
        "href": "https://www.k-village.co.kr/goods/KWP26146O8",
        "href_clean": "https://www.k-village.co.kr/goods/KWP26146O8",
        "plan_start": "",
        "plan_end": "",
        "img_url": "https://contents.k-village.co.kr/Prod/2026/K/KWP26146O8/KWP26146O8_DG_01.JPG/k2dims/resize/540/extent/540x720/optimize",
        "img_local": "k2_11_400a5f51c3.jpg",
        "img_status": "ok",
        "img_w": "540",
        "img_h": "720",
        "img_bytes": "21719",
        "img_signature": "60b41e0aca64bbae",
        "brand_resolved_url": "https://www.k-village.co.kr/K2",
        "extract_source": "generic_fallback",
        "confidence_score": "0.55",
        "is_fallback": "1",
        "is_primary_hero": "0",
        "landing_title": "",
        "landing_subtitle": "",
        "landing_summary": "",
        "landing_keywords": "",
        "landing_category": "",
        "landing_text_status": "skipped"
      },
      "curr": {
        "date": "2026-04-21",
        "brand_key": "k2",
        "brand_name": "K2",
        "rank": "3",
        "title": "K2",
        "href": "https://www.k-village.co.kr/goods/KWP26146O8",
        "href_clean": "https://www.k-village.co.kr/goods/KWP26146O8",
        "plan_start": "",
        "plan_end": "",
        "img_url": "https://contents.k-village.co.kr/Prod/2026/K/KWP26146O8/KWP26146O8_DG_01.JPG/k2dims/resize/540/extent/540x720/optimize",
        "img_local": "k2_12_400a5f51c3.jpg",
        "img_status": "ok",
        "img_w": "540",
        "img_h": "720",
        "img_bytes": "21719",
        "img_signature": "60b41e0aca64bbae",
        "brand_resolved_url": "https://www.k-village.co.kr/K2",
        "extract_source": "generic_fallback",
        "confidence_score": "0.55",
        "is_fallback": "1",
        "is_primary_hero": "0",
        "landing_title": "",
        "landing_subtitle": "",
        "landing_summary": "",
        "landing_keywords": "",
        "landing_category": "",
        "landing_text_status": "skipped"
      }
    },
    {
      "identity": "href:https://www.montbell.co.kr/bbs/login.php?url=https%3A%2F%2Fwww.montbell.co.kr%2F",
      "brand_key": "montbell",
      "rank": "2",
      "prev_rank": "4",
      "subtype": "image_changed",
      "subtypes": [
        "rank_shift",
        "image_changed"
      ],
      "diffs": {
        "rank": {
          "prev": "4",
          "curr": "2"
        },
        "img_local": {
          "prev": "montbell_2_0ce6718e51.jpg",
          "curr": "montbell_1_0ce6718e51.jpg"
        }
      },
      "prev": {
        "date": "2026-04-20",
        "brand_key": "montbell",
        "brand_name": "Montbell",
        "rank": "4",
        "title": "montbell",
        "href": "https://www.montbell.co.kr/bbs/login.php?url=https://www.montbell.co.kr/",
        "href_clean": "https://www.montbell.co.kr/bbs/login.php?url=https%3A%2F%2Fwww.montbell.co.kr%2F",
        "plan_start": "",
        "plan_end": "",
        "img_url": "https://www.montbell.co.kr/data/apms/background/2603_750x1050_new_2.jpg",
        "img_local": "montbell_2_0ce6718e51.jpg",
        "img_status": "ok",
        "img_w": "750",
        "img_h": "1050",
        "img_bytes": "119668",
        "img_signature": "28f43fd7f96d0898",
        "brand_resolved_url": "https://www.montbell.co.kr/",
        "extract_source": "generic_fallback",
        "confidence_score": "0.55",
        "is_fallback": "1",
        "is_primary_hero": "0",
        "landing_title": "",
        "landing_subtitle": "",
        "landing_summary": "",
        "landing_keywords": "",
        "landing_category": "",
        "landing_text_status": "skipped"
      },
      "curr": {
        "date": "2026-04-21",
        "brand_key": "montbell",
        "brand_name": "Montbell",
        "rank": "2",
        "title": "montbell",
        "href": "https://www.montbell.co.kr/bbs/login.php?url=https://www.montbell.co.kr/",
        "href_clean": "https://www.montbell.co.kr/bbs/login.php?url=https%3A%2F%2Fwww.montbell.co.kr%2F",
        "plan_start": "",
        "plan_end": "",
        "img_url": "https://www.montbell.co.kr/data/apms/background/2603_750x1050_new_2.jpg",
        "img_local": "montbell_1_0ce6718e51.jpg",
        "img_status": "ok",
        "img_w": "750",
        "img_h": "1050",
        "img_bytes": "119668",
        "img_signature": "28f43fd7f96d0898",
        "brand_resolved_url": "https://www.montbell.co.kr/",
        "extract_source": "generic_fallback",
        "confidence_score": "0.55",
        "is_fallback": "1",
        "is_primary_hero": "0",
        "landing_title": "",
        "landing_subtitle": "",
        "landing_summary": "",
        "landing_keywords": "",
        "landing_category": "",
        "landing_text_status": "skipped"
      }
    },
    {
      "identity": "href:https://www.montbell.co.kr/shop/event.php?ev_id=1772169256",
      "brand_key": "montbell",
      "rank": "4",
      "prev_rank": "5",
      "subtype": "rank_shift",
      "subtypes": [
        "rank_shift"
      ],
      "diffs": {
        "rank": {
          "prev": "5",
          "curr": "4"
        }
      },
      "prev": {
        "date": "2026-04-20",
        "brand_key": "montbell",
        "brand_name": "Montbell",
        "rank": "5",
        "title": "메인 배너",
        "href": "https://www.montbell.co.kr/shop/event.php?ev_id=1772169256",
        "href_clean": "https://www.montbell.co.kr/shop/event.php?ev_id=1772169256",
        "plan_start": "",
        "plan_end": "",
        "img_url": "https://www.montbell.co.kr/data/apms/background/2603_1920x800_new_2.jpg",
        "img_local": "montbell_3_4cee8ccf87.jpg",
        "img_status": "ok",
        "img_w": "1100",
        "img_h": "458",
        "img_bytes": "77110",
        "img_signature": "c7bf30aea9d5472d",
        "brand_resolved_url": "https://www.montbell.co.kr/",
        "extract_source": "hero_slider_container",
        "confidence_score": "0.88",
        "is_fallback": "0",
        "is_primary_hero": "0",
        "landing_title": "",
        "landing_subtitle": "",
        "landing_summary": "",
        "landing_keywords": "",
        "landing_category": "",
        "landing_text_status": "skipped"
      },
      "curr": {
        "date": "2026-04-21",
        "brand_key": "montbell",
        "brand_name": "Montbell",
        "rank": "4",
        "title": "메인 배너",
        "href": "https://www.montbell.co.kr/shop/event.php?ev_id=1772169256",
        "href_clean": "https://www.montbell.co.kr/shop/event.php?ev_id=1772169256",
        "plan_start": "",
        "plan_end": "",
        "img_url": "https://www.montbell.co.kr/data/apms/background/2603_1920x800_new_2.jpg",
        "img_local": "montbell_3_4cee8ccf87.jpg",
        "img_status": "ok",
        "img_w": "1100",
        "img_h": "458",
        "img_bytes": "77110",
        "img_signature": "c7bf30aea9d5472d",
        "brand_resolved_url": "https://www.montbell.co.kr/",
        "extract_source": "hero_slider_container",
        "confidence_score": "0.88",
        "is_fallback": "0",
        "is_primary_hero": "0",
        "landing_title": "",
        "landing_subtitle": "",
        "landing_summary": "",
        "landing_keywords": "",
        "landing_category": "",
        "landing_text_status": "skipped"
      }
    },
    {
      "identity": "href:https://www.montbell.co.kr/shop/event.php?ev_id=1773639157",
      "brand_key": "montbell",
      "rank": "5",
      "prev_rank": "6",
      "subtype": "image_changed",
      "subtypes": [
        "rank_shift",
        "image_changed"
      ],
      "diffs": {
        "rank": {
          "prev": "6",
          "curr": "5"
        },
        "img_local": {
          "prev": "montbell_8_ef3ea8055a.jpg",
          "curr": "montbell_7_ef3ea8055a.jpg"
        }
      },
      "prev": {
        "date": "2026-04-20",
        "brand_key": "montbell",
        "brand_name": "Montbell",
        "rank": "6",
        "title": "#26SS NEW ARRIVAL",
        "href": "https://www.montbell.co.kr/shop/event.php?ev_id=1773639157",
        "href_clean": "https://www.montbell.co.kr/shop/event.php?ev_id=1773639157",
        "plan_start": "",
        "plan_end": "",
        "img_url": "https://www.montbell.co.kr/data/event/1773639157_s",
        "img_local": "montbell_8_ef3ea8055a.jpg",
        "img_status": "ok",
        "img_w": "937",
        "img_h": "1150",
        "img_bytes": "210988",
        "img_signature": "391cad50c736cf3e",
        "brand_resolved_url": "https://www.montbell.co.kr/",
        "extract_source": "generic_fallback",
        "confidence_score": "0.55",
        "is_fallback": "1",
        "is_primary_hero": "0",
        "landing_title": "",
        "landing_subtitle": "",
        "landing_summary": "",
        "landing_keywords": "",
        "landing_category": "",
        "landing_text_status": "skipped"
      },
      "curr": {
        "date": "2026-04-21",
        "brand_key": "montbell",
        "brand_name": "Montbell",
        "rank": "5",
        "title": "#26SS NEW ARRIVAL",
        "href": "https://www.montbell.co.kr/shop/event.php?ev_id=1773639157",
        "href_clean": "https://www.montbell.co.kr/shop/event.php?ev_id=1773639157",
        "plan_start": "",
        "plan_end": "",
        "img_url": "https://www.montbell.co.kr/data/event/1773639157_s",
        "img_local": "montbell_7_ef3ea8055a.jpg",
        "img_status": "ok",
        "img_w": "937",
        "img_h": "1150",
        "img_bytes": "210988",
        "img_signature": "391cad50c736cf3e",
        "brand_resolved_url": "https://www.montbell.co.kr/",
        "extract_source": "generic_fallback",
        "confidence_score": "0.55",
        "is_fallback": "1",
        "is_primary_hero": "0",
        "landing_title": "",
        "landing_subtitle": "",
        "landing_summary": "",
        "landing_keywords": "",
        "landing_category": "",
        "landing_text_status": "skipped"
      }
    },
    {
      "identity": "href:https://www.montbell.co.kr/shop/item.php?it_id=JBEJXUZY222",
      "brand_key": "montbell",
      "rank": "6",
      "prev_rank": "7",
      "subtype": "image_changed",
      "subtypes": [
        "rank_shift",
        "image_changed"
      ],
      "diffs": {
        "rank": {
          "prev": "7",
          "curr": "6"
        },
        "img_local": {
          "prev": "montbell_10_e801930b08.jpg",
          "curr": "montbell_9_e801930b08.jpg"
        }
      },
      "prev": {
        "date": "2026-04-20",
        "brand_key": "montbell",
        "brand_name": "Montbell",
        "rank": "7",
        "title": "메인 배너",
        "href": "https://www.montbell.co.kr/shop/item.php?it_id=JBEJXUZY222",
        "href_clean": "https://www.montbell.co.kr/shop/item.php?it_id=JBEJXUZY222",
        "plan_start": "",
        "plan_end": "",
        "img_url": "https://www.montbell.co.kr/data/item/product/thumb-JBEJXUZY222_1000x1000_01_230x230.jpg",
        "img_local": "montbell_10_e801930b08.jpg",
        "img_status": "ok",
        "img_w": "230",
        "img_h": "230",
        "img_bytes": "4344",
        "img_signature": "b063f721a4fe3ad1",
        "brand_resolved_url": "https://www.montbell.co.kr/",
        "extract_source": "generic_fallback",
        "confidence_score": "0.55",
        "is_fallback": "1",
        "is_primary_hero": "0",
        "landing_title": "",
        "landing_subtitle": "",
        "landing_summary": "",
        "landing_keywords": "",
        "landing_category": "",
        "landing_text_status": "skipped"
      },
      "curr": {
        "date": "2026-04-21",
        "brand_key": "montbell",
        "brand_name": "Montbell",
        "rank": "6",
        "title": "메인 배너",
        "href": "https://www.montbell.co.kr/shop/item.php?it_id=JBEJXUZY222",
        "href_clean": "https://www.montbell.co.kr/shop/item.php?it_id=JBEJXUZY222",
        "plan_start": "",
        "plan_end": "",
        "img_url": "https://www.montbell.co.kr/data/item/product/thumb-JBEJXUZY222_1000x1000_01_230x230.jpg",
        "img_local": "montbell_9_e801930b08.jpg",
        "img_status": "ok",
        "img_w": "230",
        "img_h": "230",
        "img_bytes": "4344",
        "img_signature": "b063f721a4fe3ad1",
        "brand_resolved_url": "https://www.montbell.co.kr/",
        "extract_source": "generic_fallback",
        "confidence_score": "0.55",
        "is_fallback": "1",
        "is_primary_hero": "0",
        "landing_title": "",
        "landing_subtitle": "",
        "landing_summary": "",
        "landing_keywords": "",
        "landing_category": "",
        "landing_text_status": "skipped"
      }
    }
  ]
}