{
  "date": "2025-08-27",
  "campaigns": [
    {
      "date": "2025-08-27",
      "year": "2025",
      "mmdd": "0827",
      "channel": "LMS",
      "send_id": "",
      "campaign": "LMS_ECOM_0912_CHUSEOK",
      "term": "-",
      "sessions": 1,
      "users": 1,
      "purchases": 0,
      "revenue": 0.0,
      "items_purchased": 0,
      "send_count": 1,
      "avg_leverage": 0.0,
      "message_title": "",
      "message_body": ""
    },
    {
      "date": "2025-08-27",
      "year": "2025",
      "mmdd": "0827",
      "channel": "EDM",
      "send_id": "",
      "campaign": "EDM_0530",
      "term": "-",
      "sessions": 1,
      "users": 1,
      "purchases": 0,
      "revenue": 0.0,
      "items_purchased": 0,
      "send_count": 1,
      "avg_leverage": 0.0,
      "message_title": "",
      "message_body": ""
    },
    {
      "date": "2025-08-27",
      "year": "2025",
      "mmdd": "0827",
      "channel": "KAKAO",
      "send_id": "",
      "campaign": "KAKAO_CH_MESSAGE_0828_FOOTWEAR",
      "term": "-",
      "sessions": 1,
      "users": 1,
      "purchases": 0,
      "revenue": 0.0,
      "items_purchased": 0,
      "send_count": 1,
      "avg_leverage": 0.0,
      "message_title": "",
      "message_body": ""
    },
    {
      "date": "2025-08-27",
      "year": "2025",
      "mmdd": "0827",
      "channel": "KAKAO",
      "send_id": "",
      "campaign": "KAKAO_alimtalk",
      "term": "KAKAO_alimtalk_0623NEWMEMBERS_1",
      "sessions": 3,
      "users": 3,
      "purchases": 2,
      "revenue": 205200.0,
      "items_purchased": 5,
      "send_count": 1,
      "avg_leverage": 0.0,
      "message_title": "",
      "message_body": ""
    },
    {
      "date": "2025-08-27",
      "year": "2025",
      "mmdd": "0827",
      "channel": "LMS",
      "send_id": "",
      "campaign": "LMS_ECOM_1228_NEWYEAR",
      "term": "-",
      "sessions": 1,
      "users": 1,
      "purchases": 0,
      "revenue": 0.0,
      "items_purchased": 0,
      "send_count": 1,
      "avg_leverage": 0.0,
      "message_title": "",
      "message_body": ""
    },
    {
      "date": "2025-08-27",
      "year": "2025",
      "mmdd": "0827",
      "channel": "KAKAO",
      "send_id": "",
      "campaign": "KAKAO_CH_MESSAGE_0421_COUPON",
      "term": "-",
      "sessions": 1,
      "users": 1,
      "purchases": 0,
      "revenue": 0.0,
      "items_purchased": 0,
      "send_count": 1,
      "avg_leverage": 0.0,
      "message_title": "",
      "message_body": ""
    },
    {
      "date": "2025-08-27",
      "year": "2025",
      "mmdd": "0827",
      "channel": "KAKAO",
      "send_id": "",
      "campaign": "KAKAO_CH_MENU_0821_EFW",
      "term": "-",
      "sessions": 2,
      "users": 2,
      "purchases": 0,
      "revenue": 0.0,
      "items_purchased": 0,
      "send_count": 1,
      "avg_leverage": 0.0,
      "message_title": "",
      "message_body": ""
    },
    {
      "date": "2025-08-27",
      "year": "2025",
      "mmdd": "0827",
      "channel": "KAKAO",
      "send_id": "",
      "campaign": "KAKAO_alimtalk",
      "term": "-",
      "sessions": 3,
      "users": 3,
      "purchases": 0,
      "revenue": 0.0,
      "items_purchased": 0,
      "send_count": 1,
      "avg_leverage": 0.0,
      "message_title": "",
      "message_body": ""
    },
    {
      "date": "2025-08-27",
      "year": "2025",
      "mmdd": "0827",
      "channel": "KAKAO",
      "send_id": "",
      "campaign": "KAKAO_CH_MESSAGE_0807_MEMBER",
      "term": "-",
      "sessions": 3,
      "users": 3,
      "purchases": 0,
      "revenue": 0.0,
      "items_purchased": 0,
      "send_count": 1,
      "avg_leverage": 0.0,
      "message_title": "",
      "message_body": ""
    },
    {
      "date": "2025-08-27",
      "year": "2025",
      "mmdd": "0827",
      "channel": "KAKAO",
      "send_id": "",
      "campaign": "KAKAO_CH_MENU_0828_FOOTWEAR",
      "term": "-",
      "sessions": 3,
      "users": 3,
      "purchases": 0,
      "revenue": 0.0,
      "items_purchased": 0,
      "send_count": 1,
      "avg_leverage": 0.0,
      "message_title": "",
      "message_body": ""
    },
    {
      "date": "2025-08-27",
      "year": "2025",
      "mmdd": "0827",
      "channel": "KAKAO",
      "send_id": "",
      "campaign": "KAKAO_CH_MENU_1024_NEW_MEN",
      "term": "-",
      "sessions": 5,
      "users": 4,
      "purchases": 0,
      "revenue": 0.0,
      "items_purchased": 0,
      "send_count": 1,
      "avg_leverage": 0.0,
      "message_title": "",
      "message_body": ""
    },
    {
      "date": "2025-08-27",
      "year": "2025",
      "mmdd": "0827",
      "channel": "KAKAO",
      "send_id": "",
      "campaign": "KAKAO_alimtalk",
      "term": "KAKAO_alimtalk_0623NEWMEMBERS_2",
      "sessions": 1,
      "users": 1,
      "purchases": 1,
      "revenue": 69000.0,
      "items_purchased": 1,
      "send_count": 1,
      "avg_leverage": 0.0,
      "message_title": "",
      "message_body": ""
    },
    {
      "date": "2025-08-27",
      "year": "2025",
      "mmdd": "0827",
      "channel": "KAKAO",
      "send_id": "",
      "campaign": "KAKAO_CH_MESSAGE_0930_DISNEY",
      "term": "-",
      "sessions": 1,
      "users": 1,
      "purchases": 0,
      "revenue": 0.0,
      "items_purchased": 0,
      "send_count": 1,
      "avg_leverage": 0.0,
      "message_title": "",
      "message_body": ""
    },
    {
      "date": "2025-08-27",
      "year": "2025",
      "mmdd": "0827",
      "channel": "KAKAO",
      "send_id": "",
      "campaign": "KAKAO_CH_MENU_0821_WINDBREAKER",
      "term": "-",
      "sessions": 1,
      "users": 1,
      "purchases": 0,
      "revenue": 0.0,
      "items_purchased": 0,
      "send_count": 1,
      "avg_leverage": 0.0,
      "message_title": "",
      "message_body": ""
    },
    {
      "date": "2025-08-27",
      "year": "2025",
      "mmdd": "0827",
      "channel": "KAKAO",
      "send_id": "",
      "campaign": "KAKAO_CH_MESSAGE_0807_BTS",
      "term": "-",
      "sessions": 4,
      "users": 4,
      "purchases": 0,
      "revenue": 0.0,
      "items_purchased": 0,
      "send_count": 1,
      "avg_leverage": 0.0,
      "message_title": "",
      "message_body": ""
    },
    {
      "date": "2025-08-27",
      "year": "2025",
      "mmdd": "0827",
      "channel": "KAKAO",
      "send_id": "",
      "campaign": "KAKAO_CH_MESSAGE_0502_TSHIRTS",
      "term": "-",
      "sessions": 1,
      "users": 1,
      "purchases": 0,
      "revenue": 0.0,
      "items_purchased": 0,
      "send_count": 1,
      "avg_leverage": 0.0,
      "message_title": "",
      "message_body": ""
    },
    {
      "date": "2025-08-27",
      "year": "2025",
      "mmdd": "0827",
      "channel": "LMS",
      "send_id": "",
      "campaign": "LMS_ECOM_0830_CHUSEOK?cmpmid=kk",
      "term": "-",
      "sessions": 1,
      "users": 1,
      "purchases": 0,
      "revenue": 0.0,
      "items_purchased": 0,
      "send_count": 1,
      "avg_leverage": 0.0,
      "message_title": "",
      "message_body": ""
    },
    {
      "date": "2025-08-27",
      "year": "2025",
      "mmdd": "0827",
      "channel": "LMS",
      "send_id": "",
      "campaign": "LMS_ECOM_0627_Waterproof",
      "term": "-",
      "sessions": 1,
      "users": 1,
      "purchases": 0,
      "revenue": 0.0,
      "items_purchased": 0,
      "send_count": 1,
      "avg_leverage": 0.0,
      "message_title": "",
      "message_body": ""
    },
    {
      "date": "2025-08-27",
      "year": "2025",
      "mmdd": "0827",
      "channel": "EDM",
      "send_id": "",
      "campaign": "EDM_1121",
      "term": "-",
      "sessions": 1,
      "users": 1,
      "purchases": 0,
      "revenue": 0.0,
      "items_purchased": 0,
      "send_count": 1,
      "avg_leverage": 0.0,
      "message_title": "",
      "message_body": ""
    },
    {
      "date": "2025-08-27",
      "year": "2025",
      "mmdd": "0827",
      "channel": "KAKAO",
      "send_id": "",
      "campaign": "KAKAO_CH_event",
      "term": "kakao_coupon_welcom",
      "sessions": 1,
      "users": 1,
      "purchases": 0,
      "revenue": 0.0,
      "items_purchased": 0,
      "send_count": 1,
      "avg_leverage": 0.0,
      "message_title": "",
      "message_body": ""
    },
    {
      "date": "2025-08-27",
      "year": "2025",
      "mmdd": "0827",
      "channel": "LMS",
      "send_id": "",
      "campaign": "LMS_ECOM_0821_EFW",
      "term": "-",
      "sessions": 10,
      "users": 9,
      "purchases": 0,
      "revenue": 0.0,
      "items_purchased": 0,
      "send_count": 1,
      "avg_leverage": 0.0,
      "message_title": "",
      "message_body": ""
    },
    {
      "date": "2025-08-27",
      "year": "2025",
      "mmdd": "0827",
      "channel": "LMS",
      "send_id": "",
      "campaign": "LMS_ECOM_0821_EFW",
      "term": "LMS_ECOM_0821_EFW",
      "sessions": 23,
      "users": 17,
      "purchases": 0,
      "revenue": 0.0,
      "items_purchased": 0,
      "send_count": 0,
      "avg_leverage": 0.0,
      "message_title": "",
      "message_body": ""
    },
    {
      "date": "2025-08-27",
      "year": "2025",
      "mmdd": "0827",
      "channel": "LMS",
      "send_id": "",
      "campaign": "LMS_ECOM_0801_bundle",
      "term": "-",
      "sessions": 2,
      "users": 2,
      "purchases": 0,
      "revenue": 0.0,
      "items_purchased": 0,
      "send_count": 1,
      "avg_leverage": 0.0,
      "message_title": "",
      "message_body": ""
    },
    {
      "date": "2025-08-27",
      "year": "2025",
      "mmdd": "0827",
      "channel": "LMS",
      "send_id": "",
      "campaign": "LMS_ECOM_0801_bundle",
      "term": "LMS_ECOM_0801_bundle",
      "sessions": 2,
      "users": 2,
      "purchases": 0,
      "revenue": 0.0,
      "items_purchased": 0,
      "send_count": 0,
      "avg_leverage": 0.0,
      "message_title": "",
      "message_body": ""
    },
    {
      "date": "2025-08-27",
      "year": "2025",
      "mmdd": "0827",
      "channel": "KAKAO",
      "send_id": "",
      "campaign": "KAKAO_CH_MESSAGE_0717_BACKPACK",
      "term": "-",
      "sessions": 2,
      "users": 2,
      "purchases": 0,
      "revenue": 0.0,
      "items_purchased": 0,
      "send_count": 1,
      "avg_leverage": 0.0,
      "message_title": "",
      "message_body": ""
    },
    {
      "date": "2025-08-27",
      "year": "2025",
      "mmdd": "0827",
      "channel": "KAKAO",
      "send_id": "",
      "campaign": "KAKAO_CH_MENU_1024_NEW_WOMEN",
      "term": "-",
      "sessions": 1,
      "users": 1,
      "purchases": 0,
      "revenue": 0.0,
      "items_purchased": 0,
      "send_count": 1,
      "avg_leverage": 0.0,
      "message_title": "",
      "message_body": ""
    }
  ],
  "products": [
    {
      "date": "2025-08-27",
      "channel": "KAKAO",
      "send_id": "",
      "campaign": "KAKAO_alimtalk",
      "term": "KAKAO_alimtalk_0623NEWMEMBERS_2",
      "item_id": "C66YU0369010",
      "item_name": "Bonre Forest™ 20L Packable Backpack",
      "items": 1,
      "revenue": 69000.0
    },
    {
      "date": "2025-08-27",
      "channel": "KAKAO",
      "send_id": "",
      "campaign": "KAKAO_alimtalk",
      "term": "KAKAO_alimtalk_0623NEWMEMBERS_1",
      "item_id": "C56CT9272084",
      "item_name": "Provisions™ Ball Cap",
      "items": 1,
      "revenue": 21000.0
    },
    {
      "date": "2025-08-27",
      "channel": "KAKAO",
      "send_id": "",
      "campaign": "KAKAO_alimtalk",
      "term": "KAKAO_alimtalk_0623NEWMEMBERS_1",
      "item_id": "C66YU0369060",
      "item_name": "Bonre Forest™ 20L Packable Backpack",
      "items": 1,
      "revenue": 69000.0
    },
    {
      "date": "2025-08-27",
      "channel": "KAKAO",
      "send_id": "",
      "campaign": "KAKAO_alimtalk",
      "term": "KAKAO_alimtalk_0623NEWMEMBERS_1",
      "item_id": "C66YU0369010",
      "item_name": "Bonre Forest™ 20L Packable Backpack",
      "items": 1,
      "revenue": 69000.0
    },
    {
      "date": "2025-08-27",
      "channel": "KAKAO",
      "send_id": "",
      "campaign": "KAKAO_alimtalk",
      "term": "KAKAO_alimtalk_0623NEWMEMBERS_1",
      "item_id": "C62AE5592279",
      "item_name": "Explorers Canyon™ Back SS Tee",
      "items": 1,
      "revenue": 39200.0
    },
    {
      "date": "2025-08-27",
      "channel": "KAKAO",
      "send_id": "",
      "campaign": "KAKAO_alimtalk",
      "term": "KAKAO_alimtalk_0623NEWMEMBERS_1",
      "item_id": "C46YU9607767",
      "item_name": "Cove Heights Park™ mid socks",
      "items": 1,
      "revenue": 7000.0
    }
  ]
}